MVDumpToSQL/__init__.py
MVDumpToSQL/example.py
MVDumpToSQL-0.0.2.dist-info/LICENSE.txt
MVDumpToSQL-0.0.2.dist-info/METADATA
MVDumpToSQL-0.0.2.dist-info/WHEEL
MVDumpToSQL-0.0.2.dist-info/top_level.txt
MVDumpToSQL-0.0.2.dist-info/RECORD
