Metadata-Version: 2.1
Name: MVDumpToSQL
Version: 0.0.2
Summary: un test
Home-page: https://github.com/MV-Projects/question-creater-backend
Author: Mathieu Comeau
Author-email: mathieu_comeau@videotron.ca
License: UNKNOWN
Project-URL: Bug Tracker, https://github.com/pypa/sampleproject/issues
Platform: UNKNOWN
Classifier: Programming Language :: Python :: 3
Classifier: License :: OSI Approved :: MIT License
Classifier: Operating System :: OS Independent
Requires-Python: >=3.6
License-File: LICENSE.txt
